recsyspy/__init__.py
recsyspy-0.0.4.dist-info/LICENSE
recsyspy-0.0.4.dist-info/METADATA
recsyspy-0.0.4.dist-info/WHEEL
recsyspy-0.0.4.dist-info/top_level.txt
recsyspy-0.0.4.dist-info/RECORD
