Metadata-Version: 2.1
Name: recsyspy
Version: 0.0.4
Summary: The Recommender Systems Python Package
Author-email: Markus Lill <markus.lill@gmx.de>
Project-URL: Homepage, https://github.com/malill/recsyspy
Project-URL: Bug Tracker, https://github.com/malill/recsyspy/issues
Classifier: Programming Language :: Python :: 3
Classifier: License :: OSI Approved :: Apache Software License
Classifier: Operating System :: OS Independent
Classifier: Topic :: Scientific/Engineering :: Human Machine Interfaces
Requires-Python: >=3.7
License-File: LICENSE
Requires-Dist: pandas (>=1.4.0)
Requires-Dist: numpy (>=1.22.0)
Provides-Extra: dev
Requires-Dist: autoflake ; extra == 'dev'
Requires-Dist: black ; extra == 'dev'
Requires-Dist: build ; extra == 'dev'
Requires-Dist: coverage ; extra == 'dev'
Requires-Dist: flake8 ; extra == 'dev'
Requires-Dist: isort ; extra == 'dev'
Requires-Dist: mypy ; extra == 'dev'
Requires-Dist: pre-commit ; extra == 'dev'
Requires-Dist: pytest ; extra == 'dev'
Requires-Dist: pytest-cov ; extra == 'dev'
Requires-Dist: toml ; extra == 'dev'
Requires-Dist: tox ; extra == 'dev'
Requires-Dist: twine ; extra == 'dev'
